huecontroller.py
huectl
setup.py
huectl.egg-info/PKG-INFO
huectl.egg-info/SOURCES.txt
huectl.egg-info/dependency_links.txt
huectl.egg-info/requires.txt
huectl.egg-info/top_level.txt