Metadata-Version: 1.0
Name: huectl
Version: 0.2
Summary: A very simple Philips Hue command line tool and controller class
Home-page: https://github.com/gicmo/huectl
Author: Christian Kellner
Author-email: christian@kellner.me
License: WTFPL
Platform: Windows
Platform: Linux
Platform: Solaris
Platform: Mac OS-X
Platform: Unix
